deps_helper.py
deps_helper-0.1.6.dist-info/WHEEL
deps_helper-0.1.6.dist-info/METADATA
deps_helper-0.1.6.dist-info/RECORD
