Metadata-Version: 2.1
Name: deps-helper
Version: 0.1.6
Summary: dependencies helper
Home-page: https://github.com/Ja-sonYun/deps_helper
License: MIT
Keywords: dependecy
Author: jasonyun
Author-email: killa30865@gmail.com
Requires-Python: >=3.9,<4.0
Classifier: License :: OSI Approved :: MIT License
Classifier: Programming Language :: Python :: 3
Classifier: Programming Language :: Python :: 3.10
Classifier: Programming Language :: Python :: 3.9
Project-URL: Repository, https://github.com/Ja-sonYun/deps_helper
